{
    "missBoxDialogues":[
        {
            "triggerType":"A",
            "lastEndingStatus":"",
            "dialogues":[
                {
                    "speaker":"AAA",
                    "line":"texttexttexttexttexttexttexttext"
                },
                {
                    "speaker":"BB",
                    "line":"texttexttexttexttexttexttexttexttexttexttexttexttexttexttexttexttexttexttexttexttexttexttexttext"
                }
            ]
        },
        {
            "triggerType":"B",
            "lastEndingStatus":"",
            "dialogues":[
                {
                    "speaker":"CCC",
                    "line":"texttexttexttexttexttexttexttext"
                },
                {
                    "speaker":"DD",
                    "line":"texttexttexttexttexttexttexttexttexttexttexttexttexttexttexttexttexttexttexttexttexttexttexttext"
                }
            ]
        },
        {
            "triggerType":"C",
            "lastEndingStatus":"testStatus",
            "dialogues":[
                {
                    "speaker":"CCC",
                    "line":"texttexttexttexttexttexttexttext"
                },
                {
                    "speaker":"DD",
                    "line":"texttexttexttexttexttexttexttexttexttexttexttexttexttexttexttexttexttexttexttexttexttexttexttext"
                }
            ]
        }
    ]
}